[
    {
        "id_": "home",
        "url": "/tuiter/home",
        "faIcon": {
            "prefix" : "fas",
            "iconName" : "home"
        },
        "caption": "Home"
    },

    {
        "id_": "explore",
        "url": "/tuiter/explore",
        "faIcon": {
            "prefix" : "fas",
            "iconName" : "hashtag"
        },
        "caption": "Explore"
    },

    {
        "id_": "lab",
        "url": "/",
        "faIcon": {
            "prefix" :  "fas",
            "iconName":  "flask"
        },
        "caption": "A6 Lab"
    },

    {
        "id_": "messages",
        "url": "#",
        "faIcon": {
            "prefix" :  "fas",
            "iconName":  "envelope"
        },
        "caption": "Messages"
    },

    {
        "id_": "bookmarks",
        "url": "#",
        "faIcon": {
            "prefix" :  "fas",
            "iconName":  "bookmark"
        },
        "caption": "Bookmarks"
    },

    {
        "id_": "list",
        "url": "#",
        "faIcon": {
            "prefix" :  "fas",
            "iconName":  "list"
        },
        "caption": "Lists"
    },

    {
        "id_": "user",
        "url": "/tuiter/profile",
        "faIcon": {
            "prefix" :  "fas",
            "iconName":  "user"
        },
        "caption": "Profile"
    },

    {
        "id_": "more",
        "url": "#",
        "faIcon": {
            "prefix" :  "fas",
            "iconName":  "ellipsis"
        },
        "caption": "More"
    }
]